LICENSE
MANIFEST.in
README.md
README.rst
setup.py
contrib/bash-completion/jenkins
jenkins_cli/__init__.py
jenkins_cli/cli.py
jenkins_cli/cli_arguments.py
jenkins_cli/version.py
jenkins_cli.egg-info/PKG-INFO
jenkins_cli.egg-info/SOURCES.txt
jenkins_cli.egg-info/dependency_links.txt
jenkins_cli.egg-info/entry_points.txt
jenkins_cli.egg-info/requires.txt
jenkins_cli.egg-info/top_level.txt
tests/__init__.py
tests/test_cli.py