Metadata-Version: 1.1
Name: jenkins-cli
Version: 0.2.0
Summary: Commandline interface for Jenkins
Home-page: https://github.com/LD250/jenkins-cli-python
Author: Denys Levchenko
Author-email: denis.levtchenko@gmail.com
License: http://opensource.org/licenses/MIT
Keywords: jenkins,commandline,cli
Platform: UNKNOWN
Classifier: Natural Language :: English
Classifier: Environment :: Console
Classifier: Intended Audience :: Developers
Classifier: Programming Language :: Python
Classifier: Programming Language :: Python :: 2.7
Classifier: Programming Language :: Python :: 3.4
Classifier: Programming Language :: Python :: 3.5
Classifier: License :: OSI Approved :: MIT License
